fastgm/__init__.py
fastgm/sm2.py
fastgm/sm3.cp38-win_amd64.pyd
fastgm/sm4.cp38-win_amd64.pyd
fastgm_whl-0.4.1.dist-info/LICENSE
fastgm_whl-0.4.1.dist-info/METADATA
fastgm_whl-0.4.1.dist-info/WHEEL
fastgm_whl-0.4.1.dist-info/top_level.txt
fastgm_whl-0.4.1.dist-info/RECORD
