Metadata-Version: 2.1
Name: fastgm-whl
Version: 0.4.1
Summary: Fast GMSSL Library for Python (and already built to wheels)
Home-page: https://github.com/wptoux/fastgm
Author: wptoux
Author-email: wangzhen_ok@qq.com
License: Apache
Keywords: 国密,GM,GMSSL,SM2,SM3,SM4,Cython
Classifier: Intended Audience :: Developers
Classifier: Programming Language :: Python :: 3
Requires-Python: >=2.6, <4
License-File: LICENSE
